fastapi_restful_rsp/__init__.py
fastapi_restful_rsp/custom_decorator.py
fastapi_restful_rsp/models.py
fastapi_restful_rsp/restful_rsp.py
fastapi_restful_rsp-0.1.13.dist-info/METADATA
fastapi_restful_rsp-0.1.13.dist-info/WHEEL
fastapi_restful_rsp-0.1.13.dist-info/RECORD
