Metadata-Version: 2.3
Name: fastapi-restful-rsp
Version: 0.1.13
Summary: 
Author: paleneutron
Author-email: paleneutron@outlook.com
Requires-Python: >=3.10
Classifier: Programming Language :: Python :: 3
Classifier: Programming Language :: Python :: 3.10
Classifier: Programming Language :: Python :: 3.11
Classifier: Programming Language :: Python :: 3.12
Classifier: Programming Language :: Python :: 3.13
Requires-Dist: fastapi (>=0.110.0)
